prem/__init__.py
prem/__main__.py
prem/_dist_ver.py
prem-0.1.0.dist-info/METADATA
prem-0.1.0.dist-info/WHEEL
prem-0.1.0.dist-info/entry_points.txt
prem-0.1.0.dist-info/top_level.txt
prem-0.1.0.dist-info/RECORD
