Metadata-Version: 2.4
Name: prem
Version: 0.1.0
Summary: Pipe remedy
Maintainer-email: Casper da Costa-Luis <casper.dcl@physics.org>
License: MPL-2.0
Project-URL: repository, https://github.com/casperdcl/prem
Classifier: Development Status :: 2 - Pre-Alpha
Classifier: Programming Language :: Python :: 3 :: Only
Requires-Python: >=3.7
Requires-Dist: argopt
Requires-Dist: shtab
